requests_rest.py
requests_rest-0.3.2.dist-info/METADATA
requests_rest-0.3.2.dist-info/WHEEL
requests_rest-0.3.2.dist-info/top_level.txt
requests_rest-0.3.2.dist-info/RECORD
